{
	"This module includes" : "Modul ini meliputi",
	"Let's go!" : "Ayo Mulai!",
	"Exams" : "Soal",
	"Lessons" : "Materi",
	"Next" : "Lanjut",
	"Previous" : "Kembali",
	"Finish" : "Selesai",
	"of" : "dari",
	"Question" : "Pertanyaan",
	"Feedback" : "Penjelasan",
	"You fail the mock up exam" : "Anda tidak lulus latihan soal ini",
	"You passed the mock up exam" : "Anda lulus latihan soal ini",
	"Module" : "Modul",
	"Points" : "Poin",
	"Score" : "Nilai",
	"Modules" : "Modul",
	"Articles" : "Artikel",
	"About Us" : "Tentang Kami",
	"Loading" : "Memuat",
	"Under Development" : "Dalam Pengembangan",
	"Videos" : "Video"
}